README.md
setup.py
lib/ubg_dgps_manager/__init__.py
lib/ubg_dgps_manager/crtomo_mesh_manager.py
lib/ubg_dgps_manager/electrode_manager.py
lib/ubg_dgps_manager/log_helper.py
lib/ubg_dgps_manager/manager.py
lib/ubg_dgps_manager.egg-info/PKG-INFO
lib/ubg_dgps_manager.egg-info/SOURCES.txt
lib/ubg_dgps_manager.egg-info/dependency_links.txt
lib/ubg_dgps_manager.egg-info/requires.txt
lib/ubg_dgps_manager.egg-info/top_level.txt
lib/ubg_dgps_manager/help_text/help.md