Metadata-Version: 2.1
Name: ubg-dgps-manager
Version: 0.3.4
Summary: dGPS manager of the Geophysics Section of the University of Bonn
Home-page: https://github.com/geophysics-ubonn/ubg_dgps_manager
Author: Maximilian Weigand
Author-email: mweigand@geo.uni-bonn.de
License: MIT
